{
  "name": "ArmsGunUp",
  "duration": 1.0,
  "sampleRate": 60.0,
  "streamedCurveCount": 0,
  "denseCurveCount": 0,
  "constantCurveCount": 36,
  "tracks": [
    {
      "limb": "DownArmB",
      "attr": "position",
      "axis": "x",
      "curveIdx": 0,
      "keys": [
        {
          "t": 0.0,
          "v": 0.4090000092983246,
          "co": [
            0.0,
            0.0,
            0.0,
            0.4090000092983246
          ]
        },
        {
          "t": 1.0,
          "v": 0.4090000092983246,
          "co": [
            0.0,
            0.0,
            0.0,
            0.4090000092983246
          ]
        }
      ]
    },
    {
      "limb": "DownArmB",
      "attr": "position",
      "axis": "y",
      "curveIdx": 1,
      "keys": [
        {
          "t": 0.0,
          "v": -0.5649999976158142,
          "co": [
            0.0,
            0.0,
            0.0,
            -0.5649999976158142
          ]
        },
        {
          "t": 1.0,
          "v": -0.5649999976158142,
          "co": [
            0.0,
            0.0,
            0.0,
            -0.5649999976158142
          ]
        }
      ]
    },
    {
      "limb": "DownArmB",
      "attr": "position",
      "axis": "z",
      "curveIdx": 2,
      "keys": [
        {
          "t": 0.0,
          "v": -0.009449969977140427,
          "co": [
            0.0,
            0.0,
            0.0,
            -0.009449969977140427
          ]
        },
        {
          "t": 1.0,
          "v": -0.009449969977140427,
          "co": [
            0.0,
            0.0,
            0.0,
            -0.009449969977140427
          ]
        }
      ]
    },
    {
      "limb": "DownArmF",
      "attr": "position",
      "axis": "x",
      "curveIdx": 3,
      "keys": [
        {
          "t": 0.0,
          "v": 0.8159999847412109,
          "co": [
            0.0,
            0.0,
            0.0,
            0.8159999847412109
          ]
        },
        {
          "t": 1.0,
          "v": 0.8159999847412109,
          "co": [
            0.0,
            0.0,
            0.0,
            0.8159999847412109
          ]
        }
      ]
    },
    {
      "limb": "DownArmF",
      "attr": "position",
      "axis": "y",
      "curveIdx": 4,
      "keys": [
        {
          "t": 0.0,
          "v": 0.4390000104904175,
          "co": [
            0.0,
            0.0,
            0.0,
            0.4390000104904175
          ]
        },
        {
          "t": 1.0,
          "v": 0.4390000104904175,
          "co": [
            0.0,
            0.0,
            0.0,
            0.4390000104904175
          ]
        }
      ]
    },
    {
      "limb": "DownArmF",
      "attr": "position",
      "axis": "z",
      "curveIdx": 5,
      "keys": [
        {
          "t": 0.0,
          "v": -0.009449969977140427,
          "co": [
            0.0,
            0.0,
            0.0,
            -0.009449969977140427
          ]
        },
        {
          "t": 1.0,
          "v": -0.009449969977140427,
          "co": [
            0.0,
            0.0,
            0.0,
            -0.009449969977140427
          ]
        }
      ]
    },
    {
      "limb": "HandB",
      "attr": "position",
      "axis": "x",
      "curveIdx": 6,
      "keys": [
        {
          "t": 0.0,
          "v": 0.9810000061988831,
          "co": [
            0.0,
            0.0,
            0.0,
            0.9810000061988831
          ]
        },
        {
          "t": 1.0,
          "v": 0.9810000061988831,
          "co": [
            0.0,
            0.0,
            0.0,
            0.9810000061988831
          ]
        }
      ]
    },
    {
      "limb": "HandB",
      "attr": "position",
      "axis": "y",
      "curveIdx": 7,
      "keys": [
        {
          "t": 0.0,
          "v": -0.014999999664723873,
          "co": [
            0.0,
            0.0,
            0.0,
            -0.014999999664723873
          ]
        },
        {
          "t": 1.0,
          "v": -0.014999999664723873,
          "co": [
            0.0,
            0.0,
            0.0,
            -0.014999999664723873
          ]
        }
      ]
    },
    {
      "limb": "HandB",
      "attr": "position",
      "axis": "z",
      "curveIdx": 8,
      "keys": [
        {
          "t": 0.0,
          "v": -0.009449969977140427,
          "co": [
            0.0,
            0.0,
            0.0,
            -0.009449969977140427
          ]
        },
        {
          "t": 1.0,
          "v": -0.009449969977140427,
          "co": [
            0.0,
            0.0,
            0.0,
            -0.009449969977140427
          ]
        }
      ]
    },
    {
      "limb": "HandF",
      "attr": "position",
      "axis": "x",
      "curveIdx": 9,
      "keys": [
        {
          "t": 0.0,
          "v": 0.6880000233650208,
          "co": [
            0.0,
            0.0,
            0.0,
            0.6880000233650208
          ]
        },
        {
          "t": 1.0,
          "v": 0.6880000233650208,
          "co": [
            0.0,
            0.0,
            0.0,
            0.6880000233650208
          ]
        }
      ]
    },
    {
      "limb": "HandF",
      "attr": "position",
      "axis": "y",
      "curveIdx": 10,
      "keys": [
        {
          "t": 0.0,
          "v": 1.3020000457763672,
          "co": [
            0.0,
            0.0,
            0.0,
            1.3020000457763672
          ]
        },
        {
          "t": 1.0,
          "v": 1.3020000457763672,
          "co": [
            0.0,
            0.0,
            0.0,
            1.3020000457763672
          ]
        }
      ]
    },
    {
      "limb": "HandF",
      "attr": "position",
      "axis": "z",
      "curveIdx": 11,
      "keys": [
        {
          "t": 0.0,
          "v": -0.009449969977140427,
          "co": [
            0.0,
            0.0,
            0.0,
            -0.009449969977140427
          ]
        },
        {
          "t": 1.0,
          "v": -0.009449969977140427,
          "co": [
            0.0,
            0.0,
            0.0,
            -0.009449969977140427
          ]
        }
      ]
    },
    {
      "limb": "UpArmB",
      "attr": "position",
      "axis": "x",
      "curveIdx": 12,
      "keys": [
        {
          "t": 0.0,
          "v": -0.11299999803304672,
          "co": [
            0.0,
            0.0,
            0.0,
            -0.11299999803304672
          ]
        },
        {
          "t": 1.0,
          "v": -0.11299999803304672,
          "co": [
            0.0,
            0.0,
            0.0,
            -0.11299999803304672
          ]
        }
      ]
    },
    {
      "limb": "UpArmB",
      "attr": "position",
      "axis": "y",
      "curveIdx": 13,
      "keys": [
        {
          "t": 0.0,
          "v": -0.49000000953674316,
          "co": [
            0.0,
            0.0,
            0.0,
            -0.49000000953674316
          ]
        },
        {
          "t": 1.0,
          "v": -0.49000000953674316,
          "co": [
            0.0,
            0.0,
            0.0,
            -0.49000000953674316
          ]
        }
      ]
    },
    {
      "limb": "UpArmB",
      "attr": "position",
      "axis": "z",
      "curveIdx": 14,
      "keys": [
        {
          "t": 0.0,
          "v": -0.009449969977140427,
          "co": [
            0.0,
            0.0,
            0.0,
            -0.009449969977140427
          ]
        },
        {
          "t": 1.0,
          "v": -0.009449969977140427,
          "co": [
            0.0,
            0.0,
            0.0,
            -0.009449969977140427
          ]
        }
      ]
    },
    {
      "limb": "UpArmF",
      "attr": "position",
      "axis": "x",
      "curveIdx": 15,
      "keys": [
        {
          "t": 0.0,
          "v": 0.4819999933242798,
          "co": [
            0.0,
            0.0,
            0.0,
            0.4819999933242798
          ]
        },
        {
          "t": 1.0,
          "v": 0.4819999933242798,
          "co": [
            0.0,
            0.0,
            0.0,
            0.4819999933242798
          ]
        }
      ]
    },
    {
      "limb": "UpArmF",
      "attr": "position",
      "axis": "y",
      "curveIdx": 16,
      "keys": [
        {
          "t": 0.0,
          "v": -0.1469999998807907,
          "co": [
            0.0,
            0.0,
            0.0,
            -0.1469999998807907
          ]
        },
        {
          "t": 1.0,
          "v": -0.1469999998807907,
          "co": [
            0.0,
            0.0,
            0.0,
            -0.1469999998807907
          ]
        }
      ]
    },
    {
      "limb": "UpArmF",
      "attr": "position",
      "axis": "z",
      "curveIdx": 17,
      "keys": [
        {
          "t": 0.0,
          "v": -0.009449969977140427,
          "co": [
            0.0,
            0.0,
            0.0,
            -0.009449969977140427
          ]
        },
        {
          "t": 1.0,
          "v": -0.009449969977140427,
          "co": [
            0.0,
            0.0,
            0.0,
            -0.009449969977140427
          ]
        }
      ]
    },
    {
      "limb": "DownArmB",
      "attr": "eulerAngles",
      "axis": "x",
      "curveIdx": 18,
      "keys": [
        {
          "t": 0.0,
          "v": 0.0,
          "co": [
            0.0,
            0.0,
            0.0,
            0.0
          ]
        },
        {
          "t": 1.0,
          "v": 0.0,
          "co": [
            0.0,
            0.0,
            0.0,
            0.0
          ]
        }
      ]
    },
    {
      "limb": "DownArmB",
      "attr": "eulerAngles",
      "axis": "y",
      "curveIdx": 19,
      "keys": [
        {
          "t": 0.0,
          "v": 0.0,
          "co": [
            0.0,
            0.0,
            0.0,
            0.0
          ]
        },
        {
          "t": 1.0,
          "v": 0.0,
          "co": [
            0.0,
            0.0,
            0.0,
            0.0
          ]
        }
      ]
    },
    {
      "limb": "DownArmB",
      "attr": "eulerAngles",
      "axis": "z",
      "curveIdx": 20,
      "keys": [
        {
          "t": 0.0,
          "v": 122.61599731445312,
          "co": [
            0.0,
            0.0,
            0.0,
            122.61599731445312
          ]
        },
        {
          "t": 1.0,
          "v": 122.61599731445312,
          "co": [
            0.0,
            0.0,
            0.0,
            122.61599731445312
          ]
        }
      ]
    },
    {
      "limb": "DownArmF",
      "attr": "eulerAngles",
      "axis": "x",
      "curveIdx": 21,
      "keys": [
        {
          "t": 0.0,
          "v": 0.0,
          "co": [
            0.0,
            0.0,
            0.0,
            0.0
          ]
        },
        {
          "t": 1.0,
          "v": 0.0,
          "co": [
            0.0,
            0.0,
            0.0,
            0.0
          ]
        }
      ]
    },
    {
      "limb": "DownArmF",
      "attr": "eulerAngles",
      "axis": "y",
      "curveIdx": 22,
      "keys": [
        {
          "t": 0.0,
          "v": 0.0,
          "co": [
            0.0,
            0.0,
            0.0,
            0.0
          ]
        },
        {
          "t": 1.0,
          "v": 0.0,
          "co": [
            0.0,
            0.0,
            0.0,
            0.0
          ]
        }
      ]
    },
    {
      "limb": "DownArmF",
      "attr": "eulerAngles",
      "axis": "z",
      "curveIdx": 23,
      "keys": [
        {
          "t": 0.0,
          "v": 190.57699584960938,
          "co": [
            0.0,
            0.0,
            0.0,
            190.57699584960938
          ]
        },
        {
          "t": 1.0,
          "v": 190.57699584960938,
          "co": [
            0.0,
            0.0,
            0.0,
            190.57699584960938
          ]
        }
      ]
    },
    {
      "limb": "HandB",
      "attr": "eulerAngles",
      "axis": "x",
      "curveIdx": 24,
      "keys": [
        {
          "t": 0.0,
          "v": 0.0,
          "co": [
            0.0,
            0.0,
            0.0,
            0.0
          ]
        },
        {
          "t": 1.0,
          "v": 0.0,
          "co": [
            0.0,
            0.0,
            0.0,
            0.0
          ]
        }
      ]
    },
    {
      "limb": "HandB",
      "attr": "eulerAngles",
      "axis": "y",
      "curveIdx": 25,
      "keys": [
        {
          "t": 0.0,
          "v": 0.0,
          "co": [
            0.0,
            0.0,
            0.0,
            0.0
          ]
        },
        {
          "t": 1.0,
          "v": 0.0,
          "co": [
            0.0,
            0.0,
            0.0,
            0.0
          ]
        }
      ]
    },
    {
      "limb": "HandB",
      "attr": "eulerAngles",
      "axis": "z",
      "curveIdx": 26,
      "keys": [
        {
          "t": 0.0,
          "v": 180.0,
          "co": [
            0.0,
            0.0,
            0.0,
            180.0
          ]
        },
        {
          "t": 1.0,
          "v": 180.0,
          "co": [
            0.0,
            0.0,
            0.0,
            180.0
          ]
        }
      ]
    },
    {
      "limb": "HandF",
      "attr": "eulerAngles",
      "axis": "x",
      "curveIdx": 27,
      "keys": [
        {
          "t": 0.0,
          "v": 0.0,
          "co": [
            0.0,
            0.0,
            0.0,
            0.0
          ]
        },
        {
          "t": 1.0,
          "v": 0.0,
          "co": [
            0.0,
            0.0,
            0.0,
            0.0
          ]
        }
      ]
    },
    {
      "limb": "HandF",
      "attr": "eulerAngles",
      "axis": "y",
      "curveIdx": 28,
      "keys": [
        {
          "t": 0.0,
          "v": 0.0,
          "co": [
            0.0,
            0.0,
            0.0,
            0.0
          ]
        },
        {
          "t": 1.0,
          "v": 0.0,
          "co": [
            0.0,
            0.0,
            0.0,
            0.0
          ]
        }
      ]
    },
    {
      "limb": "HandF",
      "attr": "eulerAngles",
      "axis": "z",
      "curveIdx": 29,
      "keys": [
        {
          "t": 0.0,
          "v": 180.0,
          "co": [
            0.0,
            0.0,
            0.0,
            180.0
          ]
        },
        {
          "t": 1.0,
          "v": 180.0,
          "co": [
            0.0,
            0.0,
            0.0,
            180.0
          ]
        }
      ]
    },
    {
      "limb": "UpArmB",
      "attr": "eulerAngles",
      "axis": "x",
      "curveIdx": 30,
      "keys": [
        {
          "t": 0.0,
          "v": 0.0,
          "co": [
            0.0,
            0.0,
            0.0,
            0.0
          ]
        },
        {
          "t": 1.0,
          "v": 0.0,
          "co": [
            0.0,
            0.0,
            0.0,
            0.0
          ]
        }
      ]
    },
    {
      "limb": "UpArmB",
      "attr": "eulerAngles",
      "axis": "y",
      "curveIdx": 31,
      "keys": [
        {
          "t": 0.0,
          "v": 0.0,
          "co": [
            0.0,
            0.0,
            0.0,
            0.0
          ]
        },
        {
          "t": 1.0,
          "v": 0.0,
          "co": [
            0.0,
            0.0,
            0.0,
            0.0
          ]
        }
      ]
    },
    {
      "limb": "UpArmB",
      "attr": "eulerAngles",
      "axis": "z",
      "curveIdx": 32,
      "keys": [
        {
          "t": 0.0,
          "v": -11.97700023651123,
          "co": [
            0.0,
            0.0,
            0.0,
            -11.97700023651123
          ]
        },
        {
          "t": 1.0,
          "v": -11.97700023651123,
          "co": [
            0.0,
            0.0,
            0.0,
            -11.97700023651123
          ]
        }
      ]
    },
    {
      "limb": "UpArmF",
      "attr": "eulerAngles",
      "axis": "x",
      "curveIdx": 33,
      "keys": [
        {
          "t": 0.0,
          "v": 0.0,
          "co": [
            0.0,
            0.0,
            0.0,
            0.0
          ]
        },
        {
          "t": 1.0,
          "v": 0.0,
          "co": [
            0.0,
            0.0,
            0.0,
            0.0
          ]
        }
      ]
    },
    {
      "limb": "UpArmF",
      "attr": "eulerAngles",
      "axis": "y",
      "curveIdx": 34,
      "keys": [
        {
          "t": 0.0,
          "v": 0.0,
          "co": [
            0.0,
            0.0,
            0.0,
            0.0
          ]
        },
        {
          "t": 1.0,
          "v": 0.0,
          "co": [
            0.0,
            0.0,
            0.0,
            0.0
          ]
        }
      ]
    },
    {
      "limb": "UpArmF",
      "attr": "eulerAngles",
      "axis": "z",
      "curveIdx": 35,
      "keys": [
        {
          "t": 0.0,
          "v": 72.09600067138672,
          "co": [
            0.0,
            0.0,
            0.0,
            72.09600067138672
          ]
        },
        {
          "t": 1.0,
          "v": 72.09600067138672,
          "co": [
            0.0,
            0.0,
            0.0,
            72.09600067138672
          ]
        }
      ]
    }
  ]
}